baza/__init__.py
baza/asymmetric.py
baza/demo.py
baza/filecrypto.py
baza/hashing.py
baza/symmetric.py
baza/utils.py
baza_crypto-0.2.0.dist-info/licenses/LICENSE
baza_crypto-0.2.0.dist-info/METADATA
baza_crypto-0.2.0.dist-info/WHEEL
baza_crypto-0.2.0.dist-info/top_level.txt
baza_crypto-0.2.0.dist-info/RECORD
