Metadata-Version: 2.4
Name: baza-crypto
Version: 0.2.0
Summary: Librería de encriptación y hashing personalizable en Python
Home-page: https://github.com/Alex-Dev-Beep/baza
Author: Artemio Baza
Author-email: alexdevmega@proton.me
Classifier: Programming Language :: Python :: 3
Classifier: License :: OSI Approved :: MIT License
Classifier: Operating System :: OS Independent
Requires-Python: >=3.10
License-File: LICENSE
Requires-Dist: cryptography>=41.0
Requires-Dist: argon2-cffi>=21.3
Requires-Dist: bcrypt>=4.0
Dynamic: author
Dynamic: author-email
Dynamic: classifier
Dynamic: description
Dynamic: description-content-type
Dynamic: home-page
Dynamic: license-file
Dynamic: requires-dist
Dynamic: requires-python
Dynamic: summary
